cglbtrial5/__init__.py
cglbtrial5/conversion.py
cglbtrial5/readers/__init__.py
cglbtrial5/readers/file_reader_interface.py
cglbtrial5/readers/file_reader_manager.py
cglbtrial5/readers/file_reader_txt.py
cglbtrial5-0.5.0.dist-info/METADATA
cglbtrial5-0.5.0.dist-info/WHEEL
cglbtrial5-0.5.0.dist-info/entry_points.txt
cglbtrial5-0.5.0.dist-info/RECORD
