Metadata-Version: 2.1
Name: cglbtrial5
Version: 0.5.0
Summary: cglbtrial5 is cglbtrial5
Home-page: https://cesgenslab.cloud/
Author: CesGensLaB
Author-email: contact@cesgenlab.fr
Requires-Python: >=3.11,<4.0
Classifier: Programming Language :: Python :: 3
Classifier: Programming Language :: Python :: 3.11
Classifier: Programming Language :: Python :: 3.12
Requires-Dist: jinja2 (>=3.1.4,<4.0.0)
